tests/__init__.py
tests/classifier_test.py
tests/comparator_test.py
tests/json_solver_test.py
tests/license_test.py
tests/output_creator_test.py
tests/package_test.py
tests/solver_test.py
thoth/license_solver/__init__.py
thoth/license_solver/classifiers.py
thoth/license_solver/cli.py
thoth/license_solver/comparator.py
thoth/license_solver/exceptions.py
thoth/license_solver/json_solver.py
thoth/license_solver/licenses.py
thoth/license_solver/output_creator.py
thoth/license_solver/package.py
thoth/license_solver/py.typed
thoth/license_solver/solver.py
thoth/license_solver/data/comparator_dictionary.yaml
thoth/license_solver/data/license_dictionary.json
thoth/license_solver/data/license_without_versions.yaml
thoth/license_solver/data/pypi_classifiers.txt
thoth/license_solver/data/spdx_licenses.json
thoth_license_solver-0.1.5.dist-info/LICENSE
thoth_license_solver-0.1.5.dist-info/METADATA
thoth_license_solver-0.1.5.dist-info/WHEEL
thoth_license_solver-0.1.5.dist-info/entry_points.txt
thoth_license_solver-0.1.5.dist-info/top_level.txt
thoth_license_solver-0.1.5.dist-info/RECORD
