Metadata-Version: 2.1
Name: thoth-license-solver
Version: 0.1.5
Summary: Package and package stack license-solver for the Thoth project
Home-page: https://github.com/thoth-station/license-solver
Author: Viliam Podhajecky
Author-email: vpodhaje@redhat.com
License: GPLv3+
License-File: LICENSE
Requires-Dist: pyyaml
Requires-Dist: requests
Requires-Dist: click
Requires-Dist: thoth-common
